README.rst
setup.py
onepiece/__init__.py
onepiece/main.py
onepiece/test_onepiece.py
onepiece.egg-info/PKG-INFO
onepiece.egg-info/SOURCES.txt
onepiece.egg-info/dependency_links.txt
onepiece.egg-info/requires.txt
onepiece.egg-info/top_level.txt