Metadata-Version: 1.0
Name: onepiece
Version: 0.1.0
Summary: One Piece
Home-page: https://github.com/akun/onepiece
Author: akun
Author-email: 6awkun@gmail.com
License: MIT License
Platform: UNKNOWN
